README.rst
setup.py
aws_messaging/messaging.py
aws_messaging.egg-info/PKG-INFO
aws_messaging.egg-info/SOURCES.txt
aws_messaging.egg-info/dependency_links.txt
aws_messaging.egg-info/requires.txt
aws_messaging.egg-info/top_level.txt